taku/__init__.py
taku/dataset.py
taku/executors.py
taku/pipeline.py
taku/task.py
taku-0.7.0.dist-info/METADATA
taku-0.7.0.dist-info/WHEEL
taku-0.7.0.dist-info/top_level.txt
taku-0.7.0.dist-info/RECORD
