Metadata-Version: 2.1
Name: taku
Version: 0.7.0
Summary: Taku: Task managing made easy
Home-page: https://taku.readthedocs.io/en/latest/
Author: Jiahui Huang
Author-email: huangjh.work@outlook.com
Keywords: task,manager
Classifier: Operating System :: Unix
Classifier: License :: OSI Approved :: MIT License
Classifier: Programming Language :: Python :: 3 :: Only
Requires-Python: >=3.6
Requires-Dist: logging
Requires-Dist: omegaconf
Requires-Dist: rich
